Workbook

Sheet Cover
C11: NIKE, Inc. (NYSE: NKE) | N11: Prepared by Chetan Puvvadi
C12: 3-Statement Model, DCF Valuation & Comparable Company Analysis | N12: Portfolio Project -- Built Using CFI FMVA Formatting Conventions
C14: Table of Contents | K14: Model Checks
C16: Outputs | K16: Balance Sheet Unbalanced? | N16: =IF(SUM(Model!D78:K78)=0,"No","Yes") -> No
C17: Valuation summary dashboard: implied share price by method, key metrics, WACC assumptions. | K17: WACC Below Terminal Growth Rate? | N17: =IF(Inputs!F116>Inputs!F117,"No","Yes") -> No
C18: Inputs | K18: Diluted EPS Negative in Any Forecast Year? | N18: =IF(COUNTIF(Model!G37:K37,"<0")=0,"No","Yes") -> No
C19: All model assumptions and drivers -- revenue growth, margins, working capital, capex, capital structure, WACC.
C20: Model
C21: 3-statement model (Income Statement, Balance Sheet, Cash Flow) plus Working Capital/PP&E and Capital Structure schedules.
C22: DCF
C23: Discounted cash flow valuation -- unlevered FCF, terminal value, enterprise/equity value, sensitivity.
C24: Comps
C25: Comparable company (trading comps) analysis and NIKE implied valuation.
C31: NIKE, Inc. Financial Model -- Portfolio Project
C32: Independent work product built by Chetan Puvvadi to learn and demonstrate 3-statement modeling, DCF
C33: valuation, and comparable company analysis technique and formatting conventions in the style taught by the
C34: Corporate Finance Institute (CFI) FMVA program. This model is not affiliated with, endorsed by, or reviewed
C35: by CFI, NIKE, Inc., or any of the peer companies referenced in the Comparable Company Analysis.
... C38: not investment advice and should not be relied upon for any investment decision.

Sheet Outputs
B3: Valuation Summary Dashboard
B5: Current Share Price | D5: =Inputs!F119 -> 39.6
B7: Valuation Method | D7: Implied Share Price | E7: Upside / (Downside)
B8: DCF -- Perpetuity Growth Method | D8: =DCF!F35 -> 45.29919 | E8: =DCF!F37 -> 0.14391894
B9: DCF -- Exit Multiple Method | D9: =DCF!F36 -> 49.099603 | E9: =DCF!F38 -> 0.23988896
B10: Comps -- EV/Revenue Method | D10: =Comps!F30 -> 37.71379 | E10: =D10/D5-1 -> -0.047631577
B11: Comps -- EV/EBITDA Method | D11: =Comps!F31 -> 32.966099 | E11: =D11/D5-1 -> -0.16752274
B12: Comps -- P/E Method | D12: =Comps!F32 -> 32.489502 | E12: =D12/D5-1 -> -0.17955803
B14: KEY METRICS -- FY2026A ACTUAL vs. FY2031E FORECAST
D16: FY2026A | E16: FY2031E
B17: Total Revenue ($mm) | D17: =Model!F18 -> 46398 | E17: =Model!K18 -> 52420.806
B18: Revenue CAGR, FY26A-FY31E | E18: =(E17/D17)^(1/5)-1 -> 0.024709791
B19: Gross Margin, % | D19: =Model!F21/Model!F18 -> 0.42913488 | E19: =Model!K21/Model!K18 -> 0.447
B20: Operating Margin (EBIT), % | D20: =Model!F27/Model!F18 -> 0.081835424 | E20: =Model!K27/Model!K18 -> 0.128
B21: Net Income ($mm) | D21: =Model!F34 -> 3108 | E21: =Model!K34 -> 5069.1116
B22: Diluted EPS ($) | D22: =Model!F37 -> 2.098582 | E22: =Model!K37 -> 3.6914385
B23: Diluted Shares Outstanding (mm) | D23: =Model!F36 -> 1481 | E23: =Model!K36 -> 1373.2076
B24: Unlevered Free Cash Flow ($mm) | E24: =DCF!K13 -> 4787.9488
B26: WACC & VALUATION ASSUMPTIONS
B28: WACC | D28: =Inputs!F116 -> 0.088188305
B29: Terminal Growth Rate | D29: =Inputs!F117 -> 0.02
B30: Exit EV/EBITDA Multiple | D30: =Inputs!F118 -> 10.505676
B53: All figures in USD unless stated. See DCF and Comps sheets for full build.

Sheet Inputs
B3: Assumptions & Drivers
B5: All figures in USD millions unless stated | D5: FY2024A | E5: FY2025A | F5: FY2026A | G5: FY2027E | H5: FY2028E | I5: FY2029E | J5: FY2030E | K5: FY2031E
B7: Days in Period | D7: 365 | E7: 365 | F7: 365 | G7: 365 | H7: 365 | I7: 365 | J7: 365 | K7: 365
B10: Driver Switch | C10: 2
B12: REVENUE GROWTH
B14: North America Revenue Growth, % | E14: =Model!E9/Model!D9-1 -> -0.085249579 | F14: =Model!F9/Model!E9-1 -> 0.047976701 | G14: {=INDEX(G16:G18,$C$10)} -> 0.048 | H14: {=INDEX(H16:H18,$C$10)} -> 0.04 | I14: {=INDEX(I16:I18,$C$10)} -> 0.04 | J14: {=INDEX(J16:J18,$C$10)} -> 0.038 | K14: {=INDEX(K16:K18,$C$10)} -> 0.04
B16: Best Case | G16: 0.068 | H16: 0.06 | I16: 0.06 | J16: 0.058 | K16: 0.06
B17: Base Case | G17: 0.048 | H17: 0.04 | I17: 0.04 | J17: 0.038 | K17: 0.04
B18: Worst Case | G18: 0.028 | H18: 0.02 | I18: 0.02 | J18: 0.018 | K18: 0.02
B21: EMEA Revenue Growth, % | E21: =Model!E10/Model!D10-1 -> -0.09921364 | F21: =Model!F10/Model!E10-1 -> 0.0256996 | G21: {=INDEX(G23:G25,$C$10)} -> 0.014 | H21: {=INDEX(H23:H25,$C$10)} -> 0.025 | I21: {=INDEX(I23:I25,$C$10)} -> 0.025 | J21: {=INDEX(J23:J25,$C$10)} -> 0.025 | K21: {=INDEX(K23:K25,$C$10)} -> 0.025
B23: =B16 -> Best Case | G23: 0.034 | H23: 0.045 | I23: 0.045 | J23: 0.045 | K23: 0.045
B24: =B17 -> Base Case | G24: 0.014 | H24: 0.025 | I24: 0.025 | J24: 0.025 | K24: 0.025
B25: =B18 -> Worst Case | G25: -0.006 | H25: 0.005 | I25: 0.005 | J25: 0.005 | K25: 0.005
B28: Greater China Revenue Growth, % | E28: =Model!E11/Model!D11-1 -> -0.12710404 | F28: =Model!F11/Model!E11-1 -> -0.11220771 | G28: {=INDEX(G30:G32,$C$10)} -> -0.128 | H28: {=INDEX(H30:H32,$C$10)} -> 0.01 | I28: {=INDEX(I30:I32,$C$10)} -> 0.01 | J28: {=INDEX(J30:J32,$C$10)} -> 0.01 | K28: {=INDEX(K30:K32,$C$10)} -> 0.02
B30: =B16 -> Best Case | G30: -0.108 | H30: 0.03 | I30: 0.03 | J30: 0.03 | K30: 0.04
B31: =B17 -> Base Case | G31: -0.128 | H31: 0.01 | I31: 0.01 | J31: 0.01 | K31: 0.02
B32: =B18 -> Worst Case | G32: -0.148 | H32: -0.01 | I32: -0.01 | J32: -0.01 | K32: 0
B35: APLA Revenue Growth, % | E35: =Model!E12/Model!D12-1 -> -0.071035815 | F35: =Model!F12/Model!E12-1 -> -0.0012797952 | G35: {=INDEX(G37:G39,$C$10)} -> -0.001 | H35: {=INDEX(H37:H39,$C$10)} -> 0.03 | I35: {=INDEX(I37:I39,$C$10)} -> 0.03 | J35: {=INDEX(J37:J39,$C$10)} -> 0.035 | K35: {=INDEX(K37:K39,$C$10)} -> 0.035
B37: =B16 -> Best Case | G37: 0.019 | H37: 0.05 | I37: 0.05 | J37: 0.055 | K37: 0.055
B38: =B17 -> Base Case | G38: -0.001 | H38: 0.03 | I38: 0.03 | J38: 0.035 | K38: 0.035
B39: =B18 -> Worst Case | G39: -0.021 | H39: 0.01 | I39: 0.01 | J39: 0.015 | K39: 0.015
B42: Global Brand Divisions Revenue Growth, % | E42: =Model!E13/Model!D13-1 -> 0.066666667 | F42: =Model!F13/Model!E13-1 -> 0.020833333 | G42: {=INDEX(G44:G46,$C$10)} -> 0.02 | H42: {=INDEX(H44:H46,$C$10)} -> 0.02 | I42: {=INDEX(I44:I46,$C$10)} -> 0.02 | J42: {=INDEX(J44:J46,$C$10)} -> 0.02 | K42: {=INDEX(K44:K46,$C$10)} -> 0.02
B44: =B16 -> Best Case | G44: 0.04 | H44: 0.04 | I44: 0.04 | J44: 0.04 | K44: 0.04
B45: =B17 -> Base Case | G45: 0.02 | H45: 0.02 | I45: 0.02 | J45: 0.02 | K45: 0.02
B46: =B18 -> Worst Case | G46: 0 | H46: 0 | I46: 0 | J46: 0 | K46: 0
B49: Converse Revenue Growth, % | E49: =Model!E16/Model!D16-1 -> -0.18731988 | F49: =Model!F16/Model!E16-1 -> -0.30614657 | G49: {=INDEX(G51:G53,$C$10)} -> -0.307 | H49: {=INDEX(H51:H53,$C$10)} -> -0.05 | I49: {=INDEX(I51:I53,$C$10)} -> -0.05 | J49: {=INDEX(J51:J53,$C$10)} -> 0 | K49: {=INDEX(K51:K53,$C$10)} -> 0.02
B51: =B16 -> Best Case | G51: -0.287 | H51: -0.03 | I51: -0.03 | J51: 0.02 | K51: 0.04
B52: =B17 -> Base Case | G52: -0.307 | H52: -0.05 | I52: -0.05 | J52: 0 | K52: 0.02
B53: =B18 -> Worst Case | G53: -0.327 | H53: -0.07 | I53: -0.07 | J53: -0.02 | K53: 0
N54: Alternative: Top-Down / Bottom-Up / Regression
B56: MARGIN & OPERATING EXPENSE DRIVERS
B58: Gross Margin, % (Scenario-Driven via Driver Switch) | D58: =Model!D21/Model!D18 -> 0.44560181 | E58: =Model!E21/Model!E18 -> 0.42734674 | F58: =Model!F21/Model!F18 -> 0.42913488 | G58: {=INDEX(G60:G62,$C$10)} -> 0.435 | H58: {=INDEX(H60:H62,$C$10)} -> 0.44 | I58: {=INDEX(I60:I62,$C$10)} -> 0.443 | J58: {=INDEX(J60:J62,$C$10)} -> 0.445 | K58: {=INDEX(K60:K62,$C$10)} -> 0.447
B60: =B16 -> Best Case | G60: 0.445 | H60: 0.45 | I60: 0.453 | J60: 0.455 | K60: 0.457
B61: =B17 -> Base Case | G61: 0.435 | H61: 0.44 | I61: 0.443 | J61: 0.445 | K61: 0.447
B62: =B18 -> Worst Case | G62: 0.425 | H62: 0.43 | I62: 0.433 | J62: 0.435 | K62: 0.437
B65: Demand Creation Expense (% of Revenue) | D65: =-Model!D23/Model!D18 -> 0.083427437 | E65: =-Model!E23/Model!E18 -> 0.10125462 | F65: =-Model!F23/Model!F18 -> 0.10246131 | G65: 0.101 | H65: 0.101 | I65: 0.101 | J65: 0.101 | K65: 0.101
B66: Operating Overhead Expense (% of Revenue) | D66: =-Model!D24/Model!D18 -> 0.23930143 | E66: =-Model!E24/Model!E18 -> 0.24615086 | F66: =-Model!F24/Model!F18 -> 0.24483814 | G66: 0.238 | H66: 0.233 | I66: 0.228 | J66: 0.223 | K66: 0.218
B67: Other Income (Expense) (% of Revenue) | G67: 0 | H67: 0 | I67: 0 | J67: 0 | K67: 0
N68: Alternative: COGS Margin, Cost per Unit
B70: WORKING CAPITAL DRIVERS
B72: Receivable Days (Sales Basis) | C72: (Days) | D72: =Model!D46/Model!D18*D7 -> 31.460126 | E72: =Model!E46/Model!E18*E7 -> 37.178626 | F72: =Model!F46/Model!F18*F7 -> 46.657507 | G72: 46.7 | H72: 45 | I72: 45 | J72: 45 | K72: 45
B73: Inventory Days (COGS Basis) | C73: (Days) | D73: =Model!D47/-Model!D20*D7 -> 96.380509 | E73: =Model!E47/-Model!E20*E7 -> 103.07647 | F73: =Model!F47/-Model!F20*F7 -> 103.36637 | G73: 97 | H73: 96 | I73: 95 | J73: 95 | K73: 95
B74: Payable Days (COGS Basis) | C74: (Days) | D74: =Model!D58/-Model!D20*D7 -> 36.621773 | E74: =Model!E58/-Model!E20*E7 -> 47.88397 | F74: =Model!F58/-Model!F20*F7 -> 49.609242 | G74: 46.5 | H74: 47.5 | I74: 48 | J74: 48 | K74: 48
N75: Alternative: Use Average Balance
B77: CAPEX, DEPRECIATION & TAX DRIVERS
B79: Capital Expenditures (% of Revenue) (Scenario-Driven via Driver Switch) | D79: =-Model!D141/Model!D18 -> 0.015809353 | E79: =-Model!E141/Model!E18 -> 0.0092854521 | F79: =-Model!F141/Model!F18 -> 0.014742015 | G79: {=INDEX(G81:G83,$C$10)} -> 0.016 | H79: {=INDEX(H81:H83,$C$10)} -> 0.017 | I79: {=INDEX(I81:I83,$C$10)} -> 0.017 | J79: {=INDEX(J81:J83,$C$10)} -> 0.017 | K79: {=INDEX(K81:K83,$C$10)} -> 0.017
B81: =B16 -> Best Case | G81: 0.013 | H81: 0.014 | I81: 0.014 | J81: 0.014 | K81: 0.014
B82: =B17 -> Base Case | G82: 0.016 | H82: 0.017 | I82: 0.017 | J82: 0.017 | K82: 0.017
B83: =B18 -> Worst Case | G83: 0.02 | H83: 0.021 | I83: 0.021 | J83: 0.021 | K83: 0.021
B86: Depreciation & Amortization (% of Revenue) | D86: =-Model!D142/Model!D18 -> 0.015497839 | E86: =-Model!E142/Model!E18 -> 0.016735408 | F86: =-Model!F142/Model!F18 -> 0.016099832 | G86: 0.017 | H86: 0.017 | I86: 0.017 | J86: 0.017 | K86: 0.017
B87: Tax Rate (% of EBT) | D87: =-Model!D33/Model!D31 -> 0.14925373 | E87: =-Model!E33/Model!E31 -> 0.17142857 | F87: =-Model!F33/Model!F31 -> 0.20307692 | G87: 0.22 | H87: 0.23 | I87: 0.24 | J87: 0.24 | K87: 0.24
B89: CAPITAL STRUCTURE & CAPITAL RETURNS DRIVERS
B91: Scheduled Long-Term Debt Repayment | G91: -2000 | H91: 0 | I91: 0 | J91: 0 | K91: 0
B92: Long-Term Debt Interest Rate (Beginning Debt) | G92: 0.052 | H92: 0.052 | I92: 0.052 | J92: 0.052 | K92: 0.052
B93: Revolving Credit Line Interest Rate (Beginning Balance) | G93: 0.062 | H93: 0.062 | I93: 0.062 | J93: 0.062 | K93: 0.062
B94: Minimum Cash Balance (Revolver Draw / Sweep Target) | G94: 3000 | H94: 3000 | I94: 3000 | J94: 3000 | K94: 3000
B95: Interest Rate on Cash & Investments (Beginning Cash) | G95: 0.04 | H95: 0.04 | I95: 0.04 | J95: 0.04 | K95: 0.04
B96: Dividend per Share Growth, % | G96: 0.03 | H96: 0.03 | I96: 0.03 | J96: 0.03 | K96: 0.03
B97: Stock-Based Compensation (% of Revenue) | G97: 0.016 | H97: 0.016 | I97: 0.016 | J97: 0.016 | K97: 0.016
B98: Share Repurchases (% of Net Income) | G98: 0.5 | H98: 0.5 | I98: 0.5 | J98: 0.5 | K98: 0.5
B99: Share Count Reduction from Buybacks, % | G99: 0.015 | H99: 0.015 | I99: 0.015 | J99: 0.015 | K99: 0.015
N100: Alternative: Debt / Equity Ratio
B102: WACC & DCF VALUATION DRIVERS (point-in-time inputs -- single value in column F)
B104: Risk-Free Rate (U.S. 10-Year Treasury) | F104: 0.0473
B105: Equity Risk Premium (Damodaran, Jan-2026) | F105: 0.0423
B106: Beta (5-Year Monthly, raw) | F106: 1.12
B107: Cost of Equity (CAPM) | F107: =F104+F106*F105 -> 0.094676
B108: Pre-Tax Cost of Debt | F108: 0.053
B109: Tax Rate for WACC | F109: 0.24
B110: After-Tax Cost of Debt | F110: =F108*(1-F109) -> 0.04028
B111: Total Debt (Financial Debt, Current) | F111: 7942
B112: Market Capitalization (Current) | F112: =F119*F120 -> 58647.6
B113: Total Capital (Debt + Equity) | F113: =F111+F112 -> 66589.6
B114: Debt / Total Capital | F114: =F111/F113 -> 0.11926787
B115: Equity / Total Capital | F115: =F112/F113 -> 0.88073213
B116: WACC | F116: =F115*F107+F114*F110 -> 0.088188305
B117: Terminal Growth Rate (Perpetuity) | F117: 0.02
B118: Exit EV / EBITDA Multiple (cross-check, from Comps) | F118: =Comps!O13 -> 10.505676
B119: Current Share Price ($/sh, Aug-2026) | F119: 39.6
B120: Diluted Shares Outstanding, Current (mm) | F120: 1481

Sheet Model
B3: Income Statement
B5: All figures in USD millions unless stated | D5: FY2024A | E5: FY2025A | F5: FY2026A | G5: FY2027E | H5: FY2028E | I5: FY2029E | J5: FY2030E | K5: FY2031E
B7: NIKE BRAND REVENUE BY GEOGRAPHY
B9: North America | D9: 21396 | E9: 19572 | F9: 20511 | G9: =F9*(1+Inputs!G14) -> 21495.528 | H9: =G9*(1+Inputs!H14) -> 22355.349 | I9: =H9*(1+Inputs!I14) -> 23249.563 | J9: =I9*(1+Inputs!J14) -> 24133.046 | K9: =J9*(1+Inputs!K14) -> 25098.368
B10: EMEA | D10: 13607 | E10: 12257 | F10: 12572 | G10: =F10*(1+Inputs!G21) -> 12748.008 | H10: =G10*(1+Inputs!H21) -> 13066.708 | I10: =H10*(1+Inputs!I21) -> 13393.376 | J10: =I10*(1+Inputs!J21) -> 13728.21 | K10: =J10*(1+Inputs!K21) -> 14071.416
B11: Greater China | D11: 7545 | E11: 6586 | F11: 5847 | G11: =F11*(1+Inputs!G28) -> 5098.584 | H11: =G11*(1+Inputs!H28) -> 5149.5698 | I11: =H11*(1+Inputs!I28) -> 5201.0655 | J11: =I11*(1+Inputs!J28) -> 5253.0762 | K11: =J11*(1+Inputs!K28) -> 5358.1377
B12: APLA | D12: 6729 | E12: 6251 | F12: 6243 | G12: =F12*(1+Inputs!G35) -> 6236.757 | H12: =G12*(1+Inputs!H35) -> 6423.8597 | I12: =H12*(1+Inputs!I35) -> 6616.5755 | J12: =I12*(1+Inputs!J35) -> 6848.1556 | K12: =J12*(1+Inputs!K35) -> 7087.8411
B13: Global Brand Divisions | D13: 45 | E13: 48 | F13: 49 | G13: =F13*(1+Inputs!G42) -> 49.98 | H13: =G13*(1+Inputs!H42) -> 50.9796 | I13: =H13*(1+Inputs!I42) -> 51.999192 | J13: =I13*(1+Inputs!J42) -> 53.039176 | K13: =J13*(1+Inputs!K42) -> 54.099959
B14: NIKE Brand Revenue, Total | D14: =SUM(D9:D13) -> 49322 | E14: =SUM(E9:E13) -> 44714 | F14: =SUM(F9:F13) -> 45222 | G14: =SUM(G9:G13) -> 45628.857 | H14: =SUM(H9:H13) -> 47046.466 | I14: =SUM(I9:I13) -> 48512.579 | J14: =SUM(J9:J13) -> 50015.528 | K14: =SUM(K9:K13) -> 51669.863
B16: Converse | D16: 2082 | E16: 1692 | F16: 1174 | G16: =F16*(1+Inputs!G49) -> 813.582 | H16: =G16*(1+Inputs!H49) -> 772.9029 | I16: =H16*(1+Inputs!I49) -> 734.25775 | J16: =I16*(1+Inputs!J49) -> 734.25775 | K16: =J16*(1+Inputs!K49) -> 748.94291
B17: Corporate & Eliminations | D17: -42 | E17: -97 | F17: 2 | G17: =F17 -> 2 | H17: =G17 -> 2 | I17: =H17 -> 2 | J17: =I17 -> 2 | K17: =J17 -> 2
B18: Total Revenue | D18: =D14+D16+D17 -> 51362 | E18: =E14+E16+E17 -> 46309 | F18: =F14+F16+F17 -> 46398 | G18: =G14+G16+G17 -> 46444.439 | H18: =H14+H16+H17 -> 47821.369 | I18: =I14+I16+I17 -> 49248.837 | J18: =J14+J16+J17 -> 50751.786 | K18: =K14+K16+K17 -> 52420.806
B20: Cost of Sales | D20: -28475 | E20: -26519 | F20: -26487 | G20: =-G18*(1-Inputs!G58) -> -26241.108 | H20: =-H18*(1-Inputs!H58) -> -26779.967 | I20: =-I18*(1-Inputs!I58) -> -27431.602 | J20: =-J18*(1-Inputs!J58) -> -28167.241 | K20: =-K18*(1-Inputs!K58) -> -28988.705
B21: Gross Profit | D21: =D18+D20 -> 22887 | E21: =E18+E20 -> 19790 | F21: =F18+F20 -> 19911 | G21: =G18+G20 -> 20203.331 | H21: =H18+H20 -> 21041.403 | I21: =I18+I20 -> 21817.235 | J21: =J18+J20 -> 22584.545 | K21: =K18+K20 -> 23432.1
B23: Demand Creation Expense | D23: -4285 | E23: -4689 | F23: -4754 | G23: =-G18*Inputs!G65 -> -4690.8883 | H23: =-H18*Inputs!H65 -> -4829.9583 | I23: =-I18*Inputs!I65 -> -4974.1325 | J23: =-J18*Inputs!J65 -> -5125.9303 | K23: =-K18*Inputs!K65 -> -5294.5014
B24: Operating Overhead Expense | D24: -12291 | E24: -11399 | F24: -11360 | G24: =-G18*Inputs!G66 -> -11053.776 | H24: =-H18*Inputs!H66 -> -11142.379 | I24: =-I18*Inputs!I66 -> -11228.735 | J24: =-J18*Inputs!J66 -> -11317.648 | K24: =-K18*Inputs!K66 -> -11427.736
B25: Total SG&A | D25: =SUM(D23:D24) -> -16576 | E25: =SUM(E23:E24) -> -16088 | F25: =SUM(F23:F24) -> -16114 | G25: =SUM(G23:G24) -> -15744.665 | H25: =SUM(H23:H24) -> -15972.337 | I25: =SUM(I23:I24) -> -16202.867 | J25: =SUM(J23:J24) -> -16443.579 | K25: =SUM(K23:K24) -> -16722.237
B27: Operating Income (EBIT) | D27: =D21+D25 -> 6311 | E27: =E21+E25 -> 3702 | F27: =F21+F25 -> 3797 | G27: =G21+G25 -> 4458.6661 | H27: =H21+H25 -> 5069.0652 | I27: =I21+I25 -> 5614.3674 | J27: =J21+J25 -> 6140.9661 | K27: =K21+K25 -> 6709.8631
B29: Interest Income (Expense), net | D29: 161 | E29: 107 | F29: 50 | G29: =G155+G164+G170 -> -110.464 | H29: =H155+H164+H170 -> -74.369196 | I29: =I155+I164+I170 -> -61.197607 | J29: =J155+J164+J170 -> -51.807986 | K29: =K155+K164+K170 -> -39.979468
B30: Other Income (Expense), net | D30: 228 | E30: 76 | F30: 53 | G30: =G18*Inputs!G67 -> 0 | H30: =H18*Inputs!H67 -> 0 | I30: =I18*Inputs!I67 -> 0 | J30: =J18*Inputs!J67 -> 0 | K30: =K18*Inputs!K67 -> 0
B31: Income Before Taxes (EBT) | D31: =D27+D29+D30 -> 6700 | E31: =E27+E29+E30 -> 3885 | F31: =F27+F29+F30 -> 3900 | G31: =G27+G29+G30 -> 4348.2021 | H31: =H27+H29+H30 -> 4994.696 | I31: =I27+I29+I30 -> 5553.1698 | J31: =J27+J29+J30 -> 6089.1581 | K31: =K27+K29+K30 -> 6669.8836
B33: Income Tax Expense | D33: -1000 | E33: -666 | F33: -792 | G33: =-G31*Inputs!G87 -> -956.60447 | H33: =-H31*Inputs!H87 -> -1148.7801 | I33: =-I31*Inputs!I87 -> -1332.7608 | J33: =-J31*Inputs!J87 -> -1461.3979 | K33: =-K31*Inputs!K87 -> -1600.7721
B34: Net Income | D34: =D31+D33 -> 5700 | E34: =E31+E33 -> 3219 | F34: =F31+F33 -> 3108 | G34: =G31+G33 -> 3391.5977 | H34: =H31+H33 -> 3845.9159 | I34: =I31+I33 -> 4220.4091 | J34: =J31+J33 -> 4627.7601 | K34: =K31+K33 -> 5069.1116
B36: Diluted Shares Outstanding | C36: (mm) | D36: =D187 -> 1529.7 | E36: =E187 -> 1487.6 | F36: =F187 -> 1481 | G36: =G187 -> 1458.785 | H36: =H187 -> 1436.9032 | I36: =I187 -> 1415.3497 | J36: =J187 -> 1394.1194 | K36: =K187 -> 1373.2076
B37: Diluted EPS | D37: =D34/D36 -> 3.7262208 | E37: =E34/E36 -> 2.1638881 | F37: =F34/F36 -> 2.098582 | G37: =G34/G36 -> 2.3249469 | H37: =H34/H36 -> 2.6765309 | I37: =I34/I36 -> 2.9818844 | J37: =J34/J36 -> 3.3194861 | K37: =K34/K36 -> 3.6914385
B39: Balance Sheet
B41: All figures in USD millions unless stated | D41: FY2024A | E41: FY2025A | F41: FY2026A | G41: FY2027E | H41: FY2028E | I41: FY2029E | J41: FY2030E | K41: FY2031E
B43: ASSETS
B44: Cash & Cash Equivalents | D44: =D115 -> 9860 | E44: =E115 -> 7464 | F44: =F115 -> 7563 | G44: =G115 -> 5865.3701 | H44: =H115 -> 6194.6598 | I44: =I115 -> 6429.4004 | J44: =J115 -> 6725.1133 | K44: =K115 -> 7199.5752
B45: Short-Term Investments | D45: 1722 | E45: 1687 | F45: 1464 | G45: =F45 -> 1464 | H45: =G45 -> 1464 | I45: =H45 -> 1464 | J45: =I45 -> 1464 | K45: =J45 -> 1464
B46: Accounts Receivable, net | D46: =D125 -> 4427 | E46: =E125 -> 4717 | F46: =F125 -> 5931 | G46: =G125 -> 5942.3433 | H46: =H125 -> 5895.7853 | I46: =I125 -> 6071.7744 | J46: =J125 -> 6257.0695 | K46: =K125 -> 6462.839
B47: Inventories | D47: =D128 -> 7519 | E47: =E128 -> 7489 | F47: =F128 -> 7501 | G47: =G128 -> 6973.6643 | H47: =H128 -> 7043.4981 | I47: =I128 -> 7139.7321 | J47: =J128 -> 7331.1997 | K47: =K128 -> 7545.0055
B48: Prepaid Expenses & Other Current Assets | D48: 1854 | E48: 2005 | F48: 2144 | G48: =F48 -> 2144 | H48: =G48 -> 2144 | I48: =H48 -> 2144 | J48: =I48 -> 2144 | K48: =J48 -> 2144
B49: Total Current Assets | D49: =SUM(D44:D48) -> 25382 | E49: =SUM(E44:E48) -> 23362 | F49: =SUM(F44:F48) -> 24603 | G49: =SUM(G44:G48) -> 22389.378 | H49: =SUM(H44:H48) -> 22741.943 | I49: =SUM(I44:I48) -> 23248.907 | J49: =SUM(J44:J48) -> 23921.382 | K49: =SUM(K44:K48) -> 24815.42
B51: Property, Plant & Equipment, net | D51: =D143 -> 5000 | E51: =E143 -> 4828 | F51: =F143 -> 4796 | G51: =G143 -> 4749.5556 | H51: =H143 -> 4749.5556 | I51: =I143 -> 4749.5556 | J51: =J143 -> 4749.5556 | K51: =K143 -> 4749.5556
B52: Operating Lease Right-of-Use Assets, net | D52: 2718 | E52: 2712 | F52: 2838 | G52: =F52 -> 2838 | H52: =G52 -> 2838 | I52: =H52 -> 2838 | J52: =I52 -> 2838 | K52: =J52 -> 2838
B53: Goodwill & Intangible Assets | D53: 499 | E53: 499 | F53: 499 | G53: =F53 -> 499 | H53: =G53 -> 499 | I53: =H53 -> 499 | J53: =I53 -> 499 | K53: =J53 -> 499
B54: Deferred Tax & Other Non-Current Assets | D54: 4511 | E54: 5178 | F54: 5674 | G54: =F54 -> 5674 | H54: =G54 -> 5674 | I54: =H54 -> 5674 | J54: =I54 -> 5674 | K54: =J54 -> 5674
B55: TOTAL ASSETS | D55: =D49+SUM(D51:D54) -> 38110 | E55: =E49+SUM(E51:E54) -> 36579 | F55: =F49+SUM(F51:F54) -> 38410 | G55: =G49+SUM(G51:G54) -> 36149.933 | H55: =H49+SUM(H51:H54) -> 36502.499 | I55: =I49+SUM(I51:I54) -> 37009.462 | J55: =J49+SUM(J51:J54) -> 37681.938 | K55: =K49+SUM(K51:K54) -> 38575.975
B57: LIABILITIES
B58: Accounts Payable | D58: =D131 -> 2857 | E58: =E131 -> 3479 | F58: =F131 -> 3600 | G58: =G131 -> 3343.0453 | H58: =H131 -> 3485.0642 | I58: =I131 -> 3607.4436 | J58: =J131 -> 3704.1851 | K58: =K131 -> 3812.2133
B59: Accrued Liabilities | D59: 5725 | E59: 5916 | F59: 6092 | G59: =F59 -> 6092 | H59: =G59 -> 6092 | I59: =H59 -> 6092 | J59: =I59 -> 6092 | K59: =J59 -> 6092
B60: Income Taxes Payable | D60: 534 | E60: 669 | F60: 377 | G60: =F60 -> 377 | H60: =G60 -> 377 | I60: =H60 -> 377 | J60: =I60 -> 377 | K60: =J60 -> 377
B61: Current Operating Lease Liabilities | D61: 477 | E61: 502 | F61: 478 | G61: =F61 -> 478 | H61: =G61 -> 478 | I61: =H61 -> 478 | J61: =I61 -> 478 | K61: =J61 -> 478
B62: Total Current Liabilities | D62: =SUM(D58:D61) -> 9593 | E62: =SUM(E58:E61) -> 10566 | F62: =SUM(F58:F61) -> 10547 | G62: =SUM(G58:G61) -> 10290.045 | H62: =SUM(H58:H61) -> 10432.064 | I62: =SUM(I58:I61) -> 10554.444 | J62: =SUM(J58:J61) -> 10651.185 | K62: =SUM(K58:K61) -> 10759.213
B64: Long-Term Debt | D64: =D152 -> 8903 | E64: =E152 -> 7961 | F64: =F152 -> 7942 | G64: =G152 -> 5942 | H64: =H152 -> 5942 | I64: =I152 -> 5942 | J64: =J152 -> 5942 | K64: =K152 -> 5942
B65: Revolving Credit Line | D65: =D161 -> 0 | E65: =E161 -> 0 | F65: =F161 -> 0 | G65: =G161 -> 0 | H65: =H161 -> 0 | I65: =I161 -> 0 | J65: =J161 -> 0 | K65: =K161 -> 0
B66: Non-Current Operating Lease Liabilities | D66: 2566 | E66: 2550 | F66: 2613 | G66: =F66 -> 2613 | H66: =G66 -> 2613 | I66: =H66 -> 2613 | J66: =I66 -> 2613 | K66: =J66 -> 2613
B67: Deferred Tax & Other Non-Current Liabilities | D67: 2618 | E67: 2289 | F67: 2443 | G67: =F67 -> 2443 | H67: =G67 -> 2443 | I67: =H67 -> 2443 | J67: =I67 -> 2443 | K67: =J67 -> 2443
B68: Total Liabilities | D68: =D62+SUM(D64:D67) -> 23680 | E68: =E62+SUM(E64:E67) -> 23366 | F68: =F62+SUM(F64:F67) -> 23545 | G68: =G62+SUM(G64:G67) -> 21288.045 | H68: =H62+SUM(H64:H67) -> 21430.064 | I68: =I62+SUM(I64:I67) -> 21552.444 | J68: =J62+SUM(J64:J67) -> 21649.185 | K68: =K62+SUM(K64:K67) -> 21757.213
B70: EQUITY
B71: Common Stock & APIC | D71: =D175 -> 13412 | E71: =E175 -> 14198 | F71: =F175 -> 15161 | G71: =G175 -> 15904.111 | H71: =H175 -> 16669.253 | I71: =I175 -> 17457.234 | J71: =J175 -> 18269.263 | K71: =K175 -> 19107.996
B72: Retained Earnings (Deficit) | D72: =D182 -> 965 | E72: =E182 -> -727 | F72: =F182 -> -155 | G72: =G182 -> -901.22301 | H72: =H182 -> -1455.8183 | I72: =I182 -> -1859.2155 | J72: =J182 -> -2095.51 | K72: =K182 -> -2148.2338
B73: Accumulated Other Comprehensive Income (Loss) | D73: 53 | E73: -258 | F73: -141 | G73: =F73 -> -141 | H73: =G73 -> -141 | I73: =H73 -> -141 | J73: =I73 -> -141 | K73: =J73 -> -141
B74: Total Shareholders' Equity | D74: =SUM(D71:D73) -> 14430 | E74: =SUM(E71:E73) -> 13213 | F74: =SUM(F71:F73) -> 14865 | G74: =SUM(G71:G73) -> 14861.888 | H74: =SUM(H71:H73) -> 15072.435 | I74: =SUM(I71:I73) -> 15457.019 | J74: =SUM(J71:J73) -> 16032.753 | K74: =SUM(K71:K73) -> 16818.762
B76: Total Liabilities & Equity | D76: =D68+D74 -> 38110 | E76: =E68+E74 -> 36579 | F76: =F68+F74 -> 38410 | G76: =G68+G74 -> 36149.933 | H76: =H68+H74 -> 36502.499 | I76: =I68+I74 -> 37009.462 | J76: =J68+J74 -> 37681.938 | K76: =K68+K74 -> 38575.975
B78: Balance Sheet Check | D78: =ROUND(D55-D76,0) -> 0 | E78: =ROUND(E55-E76,0) -> 0 | F78: =ROUND(F55-F76,0) -> 0 | G78: =ROUND(G55-G76,0) -> 0 | H78: =ROUND(H55-H76,0) -> 0 | I78: =ROUND(I55-I76,0) -> 0 | J78: =ROUND(J55-J76,0) -> 0 | K78: =ROUND(K55-K76,0) -> 0
B80: Cash Flow Statement
B82: All figures in USD millions unless stated | D82: FY2024A | E82: FY2025A | F82: FY2026A | G82: FY2027E | H82: FY2028E | I82: FY2029E | J82: FY2030E | K82: FY2031E
B84: CASH FROM OPERATING ACTIVITIES
B85: Net Income | D85: =D34 -> 5700 | E85: =E34 -> 3219 | F85: =F34 -> 3108 | G85: =G34 -> 3391.5977 | H85: =H34 -> 3845.9159 | I85: =I34 -> 4220.4091 | J85: =J34 -> 4627.7601 | K85: =K34 -> 5069.1116
B86: Depreciation & Amortization | D86: =-D142 -> 796 | E86: =-E142 -> 775 | F86: =-F142 -> 747 | G86: =-G142 -> 789.55546 | H86: =-H142 -> 812.96328 | I86: =-I142 -> 837.23023 | J86: =-J142 -> 862.78035 | K86: =-K142 -> 891.15369
B87: Stock-Based Compensation | D87: =D174 -> 804 | E87: =E174 -> 709 | F87: =F174 -> 715 | G87: =G174 -> 743.11102 | H87: =H174 -> 765.14191 | I87: =I174 -> 787.98139 | J87: =J174 -> 812.02857 | K87: =K174 -> 838.73289
B88: Deferred Income Taxes | D88: -497 | E88: -288 | F88: -96 | G88: 0 | H88: 0 | I88: 0 | J88: 0 | K88: 0
B89: Amortization / Impairment & Other | D89: 48 | E89: 33 | F89: 50 | G89: 0 | H89: 0 | I89: 0 | J89: 0 | K89: 0
B90: Net Foreign Currency Adjustments | D90: -138 | E90: 37 | F90: 22 | G90: 0 | H90: 0 | I90: 0 | J90: 0 | K90: 0
B91: Change in Accounts Receivable | D91: -329 | E91: -257 | F91: -1207 | G91: =G134 -> -11.343291 | H91: =H134 -> 46.558026 | I91: =I134 -> -175.98916 | J91: =J134 -> -185.29503 | K91: =K134 -> -205.76959
B92: Change in Inventories | D92: 908 | E92: 120 | F92: -31 | G92: =G135 -> 527.33567 | H92: =H135 -> -69.833803 | I92: =I135 -> -96.233949 | J92: =J135 -> -191.46763 | K92: =K135 -> -213.80583
B93: Change in Prepaid/Other Current Assets | D93: -260 | E93: -224 | F93: 519 | G93: 0 | H93: 0 | I93: 0 | J93: 0 | K93: 0
B94: Change in Accounts Payable & Accrued Liabilities | D94: 397 | E94: -426 | F94: -959 | G94: =G136 -> -256.95473 | H94: =H136 -> 142.01891 | I94: =I136 -> 122.3794 | J94: =J136 -> 96.741539 | K94: =K136 -> 108.02821
B95: Cash Flows from Operating Activities | D95: =SUM(D85:D94) -> 7429 | E95: =SUM(E85:E94) -> 3698 | F95: =SUM(F85:F94) -> 2868 | G95: =SUM(G85:G94) -> 5183.3018 | H95: =SUM(H85:H94) -> 5542.7642 | I95: =SUM(I85:I94) -> 5695.777 | J95: =SUM(J85:J94) -> 6022.5479 | K95: =SUM(K85:K94) -> 6487.4509
B97: CASH FROM INVESTING ACTIVITIES
B98: Capital Expenditures | D98: =D141 -> -812 | E98: =E141 -> -430 | F98: =F141 -> -684 | G98: =G141 -> -743.11102 | H98: =H141 -> -812.96328 | I98: =I141 -> -837.23023 | J98: =J141 -> -862.78035 | K98: =K141 -> -891.15369
B99: Net Purchases (Sales) of Short-Term Investments | D99: 1721 | E99: 147 | F99: 261 | G99: 0 | H99: 0 | I99: 0 | J99: 0 | K99: 0
B100: Other Investing Activities | D100: -15 | E100: 8 | F100: -65 | G100: 0 | H100: 0 | I100: 0 | J100: 0 | K100: 0
B101: Cash Flows from Investing Activities | D101: =SUM(D98:D100) -> 894 | E101: =SUM(E98:E100) -> -275 | F101: =SUM(F98:F100) -> -488 | G101: =SUM(G98:G100) -> -743.11102 | H101: =SUM(H98:H100) -> -812.96328 | I101: =SUM(I98:I100) -> -837.23023 | J101: =SUM(J98:J100) -> -862.78035 | K101: =SUM(K98:K100) -> -891.15369
B103: CASH FROM FINANCING ACTIVITIES
B104: Long-Term Debt Repayment | D104: 0 | E104: -1000 | F104: 0 | G104: =G151 -> -2000 | H104: =H151 -> 0 | I104: =I151 -> 0 | J104: =J151 -> 0 | K104: =K151 -> 0
B105: Revolving Credit Line, Draw / (Repayment) | D105: 0 | E105: 0 | F105: 0 | G105: =IF((G114+G95+G101+G104+G106+G107+G108+G109+G112-Inputs!G94)<0,-(G114+G95+G101+G104+G106+G107+G108+G109+G112-Inputs!G94),-MIN((G114+G95+G101+G104+G106+G107+G108+G109+G112-Inputs!G94),G159)) -> 0 | H105: =IF((H114+H95+H101+H104+H106+H107+H108+H109+H112-Inputs!H94)<0,-(H114+H95+H101+H104+H106+H107+H108+H109+H112-Inputs!H94),-MIN((H114+H95+H101+H104+H106+H107+H108+H109+H112-Inputs!H94),H159)) -> 0 | I105: =IF((I114+I95+I101+I104+I106+I107+I108+I109+I112-Inputs!I94)<0,-(I114+I95+I101+I104+I106+I107+I108+I109+I112-Inputs!I94),-MIN((I114+I95+I101+I104+I106+I107+I108+I109+I112-Inputs!I94),I159)) -> 0 | J105: =IF((J114+J95+J101+J104+J106+J107+J108+J109+J112-Inputs!J94)<0,-(J114+J95+J101+J104+J106+J107+J108+J109+J112-Inputs!J94),-MIN((J114+J95+J101+J104+J106+J107+J108+J109+J112-Inputs!J94),J159)) -> 0 | K105: =IF((K114+K95+K101+K104+K106+K107+K108+K109+K112-Inputs!K94)<0,-(K114+K95+K101+K104+K106+K107+K108+K109+K112-Inputs!K94),-MIN((K114+K95+K101+K104+K106+K107+K108+K109+K112-Inputs!K94),K159)) -> 0
B106: Proceeds from Stock Option Exercises | D106: 667 | E106: 551 | F106: 354 | G106: 0 | H106: 0 | I106: 0 | J106: 0 | K106: 0
B107: Share Repurchases | D107: =D181 -> -4250 | E107: =E181 -> -2985 | F107: =F181 -> -146 | G107: =G181 -> -1695.7988 | H107: =H181 -> -1922.9579 | I107: =I181 -> -2110.2045 | J107: =J181 -> -2313.8801 | K107: =K181 -> -2534.5558
B108: Dividends Paid | D108: =D180 -> -2169 | E108: =E180 -> -2300 | F108: =F180 -> -2407 | G108: =G180 -> -2442.0219 | H108: =H180 -> -2477.5533 | I108: =I180 -> -2513.6017 | J108: =J180 -> -2550.1746 | K108: =K180 -> -2587.2796
B109: Other Financing Activities | D109: -136 | E109: -86 | F109: -93 | G109: 0 | H109: 0 | I109: 0 | J109: 0 | K109: 0
B110: Cash Flows from Financing Activities | D110: =SUM(D104:D109) -> -5888 | E110: =SUM(E104:E109) -> -5820 | F110: =SUM(F104:F109) -> -2292 | G110: =SUM(G104:G109) -> -6137.8207 | H110: =SUM(H104:H109) -> -4400.5112 | I110: =SUM(I104:I109) -> -4623.8062 | J110: =SUM(J104:J109) -> -4864.0546 | K110: =SUM(K104:K109) -> -5121.8354
B112: Effect of Exchange Rates on Cash | D112: -16 | E112: 1 | F112: 11 | G112: 0 | H112: 0 | I112: 0 | J112: 0 | K112: 0
B113: Net Change in Cash | D113: =D95+D101+D110+D112 -> 2419 | E113: =E95+E101+E110+E112 -> -2396 | F113: =F95+F101+F110+F112 -> 99 | G113: =G95+G101+G110+G112 -> -1697.6299 | H113: =H95+H101+H110+H112 -> 329.28972 | I113: =I95+I101+I110+I112 -> 234.74054 | J113: =J95+J101+J110+J112 -> 295.71294 | K113: =K95+K101+K110+K112 -> 474.46185
B114: Cash & Cash Equivalents, Beginning of the Year | D114: 7441 | E114: =D115 -> 9860 | F114: =E115 -> 7464 | G114: =F115 -> 7563 | H114: =G115 -> 5865.3701 | I114: =H115 -> 6194.6598 | J114: =I115 -> 6429.4004 | K114: =J115 -> 6725.1133
B115: Cash & Cash Equivalents, End of the Year | D115: =D114+D113 -> 9860 | E115: =E114+E113 -> 7464 | F115: =F114+F113 -> 7563 | G115: =G114+G113 -> 5865.3701 | H115: =H114+H113 -> 6194.6598 | I115: =I114+I113 -> 6429.4004 | J115: =J114+J113 -> 6725.1133 | K115: =K114+K113 -> 7199.5752
B117: Working Capital and PP&E Schedule
B119: All figures in USD millions unless stated | D119: FY2024A | E119: FY2025A | F119: FY2026A | G119: FY2027E | H119: FY2028E | I119: FY2029E | J119: FY2030E | K119: FY2031E
B121: Revenue | D121: =D18 -> 51362 | E121: =E18 -> 46309 | F121: =F18 -> 46398 | G121: =G18 -> 46444.439 | H121: =H18 -> 47821.369 | I121: =I18 -> 49248.837 | J121: =J18 -> 50751.786 | K121: =K18 -> 52420.806
B122: Cost of Sales | D122: =-D20 -> 28475 | E122: =-E20 -> 26519 | F122: =-F20 -> 26487 | G122: =-G20 -> 26241.108 | H122: =-H20 -> 26779.967 | I122: =-I20 -> 27431.602 | J122: =-J20 -> 28167.241 | K122: =-K20 -> 28988.705
B124: Receivable Days (Sales Basis) | C124: (Days) | D124: =Inputs!D72 -> 31.460126 | E124: =Inputs!E72 -> 37.178626 | F124: =Inputs!F72 -> 46.657507 | G124: =Inputs!G72 -> 46.7 | H124: =Inputs!H72 -> 45 | I124: =Inputs!I72 -> 45 | J124: =Inputs!J72 -> 45 | K124: =Inputs!K72 -> 45
B125: Trade and Other Receivables | D125: 4427 | E125: 4717 | F125: 5931 | G125: =G124/Inputs!G7*G121 -> 5942.3433 | H125: =H124/Inputs!H7*H121 -> 5895.7853 | I125: =I124/Inputs!I7*I121 -> 6071.7744 | J125: =J124/Inputs!J7*J121 -> 6257.0695 | K125: =K124/Inputs!K7*K121 -> 6462.839
B127: Inventory Days (COGS Basis) | C127: (Days) | D127: =Inputs!D73 -> 96.380509 | E127: =Inputs!E73 -> 103.07647 | F127: =Inputs!F73 -> 103.36637 | G127: =Inputs!G73 -> 97 | H127: =Inputs!H73 -> 96 | I127: =Inputs!I73 -> 95 | J127: =Inputs!J73 -> 95 | K127: =Inputs!K73 -> 95
B128: Inventory | D128: 7519 | E128: 7489 | F128: 7501 | G128: =G127/Inputs!G7*G122 -> 6973.6643 | H128: =H127/Inputs!H7*H122 -> 7043.4981 | I128: =I127/Inputs!I7*I122 -> 7139.7321 | J128: =J127/Inputs!J7*J122 -> 7331.1997 | K128: =K127/Inputs!K7*K122 -> 7545.0055
B130: Payable Days (COGS Basis) | C130: (Days) | D130: =Inputs!D74 -> 36.621773 | E130: =Inputs!E74 -> 47.88397 | F130: =Inputs!F74 -> 49.609242 | G130: =Inputs!G74 -> 46.5 | H130: =Inputs!H74 -> 47.5 | I130: =Inputs!I74 -> 48 | J130: =Inputs!J74 -> 48 | K130: =Inputs!K74 -> 48
B131: Trade and Other Payables | D131: 2857 | E131: 3479 | F131: 3600 | G131: =G130/Inputs!G7*G122 -> 3343.0453 | H131: =H130/Inputs!H7*H122 -> 3485.0642 | I131: =I130/Inputs!I7*I122 -> 3607.4436 | J131: =J130/Inputs!J7*J122 -> 3704.1851 | K131: =K130/Inputs!K7*K122 -> 3812.2133
B133: CASH CHANGES FROM WORKING CAPITAL
B134: Trade and Other Receivables | E134: =-(E125-D125) -> -290 | F134: =-(F125-E125) -> -1214 | G134: =-(G125-F125) -> -11.343291 | H134: =-(H125-G125) -> 46.558026 | I134: =-(I125-H125) -> -175.98916 | J134: =-(J125-I125) -> -185.29503 | K134: =-(K125-J125) -> -205.76959
...

Sheet DCF
B3: Discounted Cash Flow Valuation
B5: All figures in USD millions unless stated | D5: FY2024A | E5: FY2025A | F5: FY2026A | G5: FY2027E | H5: FY2028E | I5: FY2029E | J5: FY2030E | K5: FY2031E
B7: EBIT | G7: =Model!G27 -> 4458.6661 | H7: =Model!H27 -> 5069.0652 | I7: =Model!I27 -> 5614.3674 | J7: =Model!J27 -> 6140.9661 | K7: =Model!K27 -> 6709.8631
B8: Effective Tax Rate | G8: =Inputs!G87 -> 0.22 | H8: =Inputs!H87 -> 0.23 | I8: =Inputs!I87 -> 0.24 | J8: =Inputs!J87 -> 0.24 | K8: =Inputs!K87 -> 0.24
B9: NOPAT (EBIT, After-Tax) | G9: =G7*(1-G8) -> 3477.7596 | H9: =H7*(1-H8) -> 3903.1802 | I9: =I7*(1-I8) -> 4266.9192 | J9: =J7*(1-J8) -> 4667.1342 | K9: =K7*(1-K8) -> 5099.496
B10: Add: Depreciation & Amortization | G10: =-Model!G142 -> 789.55546 | H10: =-Model!H142 -> 812.96328 | I10: =-Model!I142 -> 837.23023 | J10: =-Model!J142 -> 862.78035 | K10: =-Model!K142 -> 891.15369
B11: Less: Capital Expenditures | G11: =Model!G141 -> -743.11102 | H11: =Model!H141 -> -812.96328 | I11: =Model!I141 -> -837.23023 | J11: =Model!J141 -> -862.78035 | K11: =Model!K141 -> -891.15369
B12: Add (Less): Net Change in Working Capital | G12: =Model!G137 -> 259.03765 | H12: =Model!H137 -> 118.74313 | I12: =Model!I137 -> -149.84371 | J12: =Model!J137 -> -280.02112 | K12: =Model!K137 -> -311.54721
B13: Unlevered Free Cash Flow | G13: =SUM(G9:G12) -> 3783.2417 | H13: =SUM(H9:H12) -> 4021.9233 | I13: =SUM(I9:I12) -> 4117.0755 | J13: =SUM(J9:J12) -> 4387.1131 | K13: =SUM(K9:K12) -> 4787.9488
B15: Discount Period (Mid-Year Convention) | G15: 0.5 | H15: 1.5 | I15: 2.5 | J15: 3.5 | K15: 4.5
B16: Discount Factor | G16: =1/(1+Inputs!F116)^G15 -> 0.95862328 | H16: =1/(1+Inputs!F116)^H15 -> 0.88093511 | I16: =1/(1+Inputs!F116)^I15 -> 0.80954289 | J16: =1/(1+Inputs!F116)^J15 -> 0.7439364 | K16: =1/(1+Inputs!F116)^K15 -> 0.68364676
B17: PV of Unlevered Free Cash Flow | G17: =G13*G16 -> 3626.7036 | H17: =H13*H16 -> 3543.0534 | I17: =I13*I16 -> 3332.9492 | J17: =J13*J16 -> 3263.7331 | K17: =K13*K16 -> 3273.2656
B19: TERMINAL VALUE
B21: Terminal Year Unlevered FCF (FY31E) | F21: =K13 -> 4787.9488
B22: Terminal Value -- Perpetuity Growth Method | F22: =F21*(1+Inputs!F117)/(Inputs!F116-Inputs!F117) -> 71620.9
B23: PV of Terminal Value (Perpetuity Growth) | F23: =F22*K16 -> 48963.396
B24: Terminal Year EBITDA (FY31E) | F24: =K7-Model!K142 -> 7601.0168
B25: Terminal Value -- Exit Multiple Cross-Check | F25: =F24*Inputs!F118 -> 79853.823
B26: PV of Terminal Value (Exit Multiple) | F26: =F25*K16 -> 54591.807
B28: ENTERPRISE & EQUITY VALUE
B30: Enterprise Value -- Perpetuity Growth Method | F30: =SUM(G17:K17)+F23 -> 66003.101
B31: Enterprise Value -- Exit Multiple Method | F31: =SUM(G17:K17)+F26 -> 71631.512
B32: Net Debt / (Net Cash) | F32: =Model!F64+Model!F65-Model!F44-Model!F45 -> -1085
B33: Equity Value -- Perpetuity Growth Method | F33: =F30-F32 -> 67088.101
B34: Equity Value -- Exit Multiple Method | F34: =F31-F32 -> 72716.512
B35: Implied Share Price -- Perpetuity Growth Method | F35: =F33/Inputs!F120 -> 45.29919
B36: Implied Share Price -- Exit Multiple Method | F36: =F34/Inputs!F120 -> 49.099603
B37: Implied Upside / (Downside) -- Perpetuity Growth | F37: =F35/Inputs!F119-1 -> 0.14391894
B38: Implied Upside / (Downside) -- Exit Multiple | F38: =F36/Inputs!F119-1 -> 0.23988896
B41: SENSITIVITY -- IMPLIED SHARE PRICE (PERPETUITY GROWTH METHOD)
B43: WACC (rows) vs. Terminal Growth Rate (columns)
B45: WACC (down) | C45: Terminal Growth Rate -> | D45: =Inputs!F117+(-0.01) -> 0.01 | E45: =Inputs!F117+(-0.005) -> 0.015 | F45: =Inputs!F117+(0) -> 0.02 | G45: =Inputs!F117+(0.005) -> 0.025 | H45: =Inputs!F117+(0.01) -> 0.03
C46: =Inputs!F116+(-0.01) -> 0.078188305 | D46: =($G$13/(1+$C46)^$G$15+$H$13/(1+$C46)^$H$15+$I$13/(1+$C46)^$I$15+$J$13/(1+$C46)^$J$15+$K$13/(1+$C46)^$K$15+($K$13*(1+D$45)/($C46-D$45))/(1+$C46)^$K$15-$F$32)/Inputs!$F$120 -> 46.627101 | E46: =($G$13/(1+$C46)^$G$15+$H$13/(1+$C46)^$H$15+$I$13/(1+$C46)^$I$15+$J$13/(1+$C46)^$J$15+$K$13/(1+$C46)^$K$15+($K$13*(1+E$45)/($C46-E$45))/(1+$C46)^$K$15-$F$32)/Inputs!$F$120 -> 49.509716 | F46: =($G$13/(1+$C46)^$G$15+$H$13/(1+$C46)^$H$15+$I$13/(1+$C46)^$I$15+$J$13/(1+$C46)^$J$15+$K$13/(1+$C46)^$K$15+($K$13*(1+F$45)/($C46-F$45))/(1+$C46)^$K$15-$F$32)/Inputs!$F$120 -> 52.887726 | G46: =($G$13/(1+$C46)^$G$15+$H$13/(1+$C46)^$H$15+$I$13/(1+$C46)^$I$15+$J$13/(1+$C46)^$J$15+$K$13/(1+$C46)^$K$15+($K$13*(1+G$45)/($C46-G$45))/(1+$C46)^$K$15-$F$32)/Inputs!$F$120 -> 56.900839 | H46: =($G$13/(1+$C46)^$G$15+$H$13/(1+$C46)^$H$15+$I$13/(1+$C46)^$I$15+$J$13/(1+$C46)^$J$15+$K$13/(1+$C46)^$K$15+($K$13*(1+H$45)/($C46-H$45))/(1+$C46)^$K$15-$F$32)/Inputs!$F$120 -> 61.746751
C47: =Inputs!F116+(-0.005) -> 0.083188305 | D47: =($G$13/(1+$C47)^$G$15+$H$13/(1+$C47)^$H$15+$I$13/(1+$C47)^$I$15+$J$13/(1+$C47)^$J$15+$K$13/(1+$C47)^$K$15+($K$13*(1+D$45)/($C47-D$45))/(1+$C47)^$K$15-$F$32)/Inputs!$F$120 -> 43.507651 | E47: =($G$13/(1+$C47)^$G$15+$H$13/(1+$C47)^$H$15+$I$13/(1+$C47)^$I$15+$J$13/(1+$C47)^$J$15+$K$13/(1+$C47)^$K$15+($K$13*(1+E$45)/($C47-E$45))/(1+$C47)^$K$15-$F$32)/Inputs!$F$120 -> 45.956427 | F47: =($G$13/(1+$C47)^$G$15+$H$13/(1+$C47)^$H$15+$I$13/(1+$C47)^$I$15+$J$13/(1+$C47)^$J$15+$K$13/(1+$C47)^$K$15+($K$13*(1+F$45)/($C47-F$45))/(1+$C47)^$K$15-$F$32)/Inputs!$F$120 -> 48.792738 | G47: =($G$13/(1+$C47)^$G$15+$H$13/(1+$C47)^$H$15+$I$13/(1+$C47)^$I$15+$J$13/(1+$C47)^$J$15+$K$13/(1+$C47)^$K$15+($K$13*(1+G$45)/($C47-G$45))/(1+$C47)^$K$15-$F$32)/Inputs!$F$120 -> 52.116487 | H47: =($G$13/(1+$C47)^$G$15+$H$13/(1+$C47)^$H$15+$I$13/(1+$C47)^$I$15+$J$13/(1+$C47)^$J$15+$K$13/(1+$C47)^$K$15+($K$13*(1+H$45)/($C47-H$45))/(1+$C47)^$K$15-$F$32)/Inputs!$F$120 -> 56.065138
C48: =Inputs!F116+(0) -> 0.088188305 | D48: =($G$13/(1+$C48)^$G$15+$H$13/(1+$C48)^$H$15+$I$13/(1+$C48)^$I$15+$J$13/(1+$C48)^$J$15+$K$13/(1+$C48)^$K$15+($K$13*(1+D$45)/($C48-D$45))/(1+$C48)^$K$15-$F$32)/Inputs!$F$120 -> 40.788131 | E48: =($G$13/(1+$C48)^$G$15+$H$13/(1+$C48)^$H$15+$I$13/(1+$C48)^$I$15+$J$13/(1+$C48)^$J$15+$K$13/(1+$C48)^$K$15+($K$13*(1+E$45)/($C48-E$45))/(1+$C48)^$K$15-$F$32)/Inputs!$F$120 -> 42.88957 | F48: =($G$13/(1+$C48)^$G$15+$H$13/(1+$C48)^$H$15+$I$13/(1+$C48)^$I$15+$J$13/(1+$C48)^$J$15+$K$13/(1+$C48)^$K$15+($K$13*(1+F$45)/($C48-F$45))/(1+$C48)^$K$15-$F$32)/Inputs!$F$120 -> 45.29919 | G48: =($G$13/(1+$C48)^$G$15+$H$13/(1+$C48)^$H$15+$I$13/(1+$C48)^$I$15+$J$13/(1+$C48)^$J$15+$K$13/(1+$C48)^$K$15+($K$13*(1+G$45)/($C48-G$45))/(1+$C48)^$K$15-$F$32)/Inputs!$F$120 -> 48.09015 | H48: =($G$13/(1+$C48)^$G$15+$H$13/(1+$C48)^$H$15+$I$13/(1+$C48)^$I$15+$J$13/(1+$C48)^$J$15+$K$13/(1+$C48)^$K$15+($K$13*(1+H$45)/($C48-H$45))/(1+$C48)^$K$15-$F$32)/Inputs!$F$120 -> 51.360753
C49: =Inputs!F116+(0.005) -> 0.093188305 | D49: =($G$13/(1+$C49)^$G$15+$H$13/(1+$C49)^$H$15+$I$13/(1+$C49)^$I$15+$J$13/(1+$C49)^$J$15+$K$13/(1+$C49)^$K$15+($K$13*(1+D$45)/($C49-D$45))/(1+$C49)^$K$15-$F$32)/Inputs!$F$120 -> 38.396403 | E49: =($G$13/(1+$C49)^$G$15+$H$13/(1+$C49)^$H$15+$I$13/(1+$C49)^$I$15+$J$13/(1+$C49)^$J$15+$K$13/(1+$C49)^$K$15+($K$13*(1+E$45)/($C49-E$45))/(1+$C49)^$K$15-$F$32)/Inputs!$F$120 -> 40.215802 | F49: =($G$13/(1+$C49)^$G$15+$H$13/(1+$C49)^$H$15+$I$13/(1+$C49)^$I$15+$J$13/(1+$C49)^$J$15+$K$13/(1+$C49)^$K$15+($K$13*(1+F$45)/($C49-F$45))/(1+$C49)^$K$15-$F$32)/Inputs!$F$120 -> 42.283792 | G49: =($G$13/(1+$C49)^$G$15+$H$13/(1+$C49)^$H$15+$I$13/(1+$C49)^$I$15+$J$13/(1+$C49)^$J$15+$K$13/(1+$C49)^$K$15+($K$13*(1+G$45)/($C49-G$45))/(1+$C49)^$K$15-$F$32)/Inputs!$F$120 -> 44.655059 | H49: =($G$13/(1+$C49)^$G$15+$H$13/(1+$C49)^$H$15+$I$13/(1+$C49)^$I$15+$J$13/(1+$C49)^$J$15+$K$13/(1+$C49)^$K$15+($K$13*(1+H$45)/($C49-H$45))/(1+$C49)^$K$15-$F$32)/Inputs!$F$120 -> 47.401596
C50: =Inputs!F116+(0.01) -> 0.098188305 | D50: =($G$13/(1+$C50)^$G$15+$H$13/(1+$C50)^$H$15+$I$13/(1+$C50)^$I$15+$J$13/(1+$C50)^$J$15+$K$13/(1+$C50)^$K$15+($K$13*(1+D$45)/($C50-D$45))/(1+$C50)^$K$15-$F$32)/Inputs!$F$120 -> 36.276692 | E50: =($G$13/(1+$C50)^$G$15+$H$13/(1+$C50)^$H$15+$I$13/(1+$C50)^$I$15+$J$13/(1+$C50)^$J$15+$K$13/(1+$C50)^$K$15+($K$13*(1+E$45)/($C50-E$45))/(1+$C50)^$K$15-$F$32)/Inputs!$F$120 -> 37.864223 | F50: =($G$13/(1+$C50)^$G$15+$H$13/(1+$C50)^$H$15+$I$13/(1+$C50)^$I$15+$J$13/(1+$C50)^$J$15+$K$13/(1+$C50)^$K$15+($K$13*(1+F$45)/($C50-F$45))/(1+$C50)^$K$15-$F$32)/Inputs!$F$120 -> 39.654794 | G50: =($G$13/(1+$C50)^$G$15+$H$13/(1+$C50)^$H$15+$I$13/(1+$C50)^$I$15+$J$13/(1+$C50)^$J$15+$K$13/(1+$C50)^$K$15+($K$13*(1+G$45)/($C50-G$45))/(1+$C50)^$K$15-$F$32)/Inputs!$F$120 -> 41.690018 | H50: =($G$13/(1+$C50)^$G$15+$H$13/(1+$C50)^$H$15+$I$13/(1+$C50)^$I$15+$J$13/(1+$C50)^$J$15+$K$13/(1+$C50)^$K$15+($K$13*(1+H$45)/($C50-H$45))/(1+$C50)^$K$15-$F$32)/Inputs!$F$120 -> 44.023712
B52: All figures in USD millions except per-share data. Explicit forecast period = FY2027E-FY2031E (5 years); mid-year discounting convention.

Sheet Comps
B3: Comparable Company Analysis
B5: Peer Company | C5: Ticker | D5: Price | E5: Dil. Shares | F5: Mkt Cap | G5: Total Debt | H5: Cash & Equiv. | I5: Net Debt | J5: Enterprise Value | K5: LTM Revenue | L5: LTM EBITDA | M5: LTM EPS | N5: EV / Rev | O5: EV / EBITDA | P5: P / E
B7: Adidas AG | C7: ADS.DE | D7: 179.16 | E7: 174 | F7: =D7*E7 -> 31173.84 | G7: 6940 | H7: 1810 | I7: =G7-H7 -> 5130 | J7: =F7+I7 -> 36303.84 | K7: 30210 | L7: 3860 | M7: 9.01 | N7: =J7/K7 -> 1.201716 | O7: =IFERROR(J7/L7,"n.m.") -> 9.4051399 | P7: =IF(M7<0,"n.m.",D7/M7) -> 19.884573
B8: Lululemon Athletica | C8: LULU | D8: 120.81 | E8: 113.6 | F8: =D8*E8 -> 13724.016 | G8: 2140 | H8: 1510 | I8: =G8-H8 -> 630 | J8: =F8+I8 -> 14354.016 | K8: 10180 | L8: 2570 | M8: 12.35 | N8: =J8/K8 -> 1.4100212 | O8: =IFERROR(J8/L8,"n.m.") -> 5.5852202 | P8: =IF(M8<0,"n.m.",D8/M8) -> 9.7821862
B9: Under Armour | C9: UAA | D9: 5.2 | E9: 429.6 | F9: =D9*E9 -> 2233.92 | G9: 1380 | H9: 396 | I9: =G9-H9 -> 984 | J9: =F9+I9 -> 3217.92 | K9: 4930 | L9: 173 | M9: -1.15 | N9: =J9/K9 -> 0.65272211 | O9: =IFERROR(J9/L9,"n.m.") -> 18.600694 | P9: =IF(M9<0,"n.m.",D9/M9) -> n.m.
B10: Deckers Brands | C10: DECK | D10: 87.76 | E10: 136.2 | F10: =D10*E10 -> 11952.912 | G10: 472 | H10: 1600 | I10: =G10-H10 -> -1128 | J10: =F10+I10 -> 10824.912 | K10: 5530 | L10: 1330 | M10: 7.05 | N10: =J10/K10 -> 1.9574886 | O10: =IFERROR(J10/L10,"n.m.") -> 8.1390316 | P10: =IF(M10<0,"n.m.",D10/M10) -> 12.448227
B11: VF Corporation | C11: VFC | D11: 13.67 | E11: 393.1 | F11: =D11*E11 -> 5373.677 | G11: 4950 | H11: 670 | I11: =G11-H11 -> 4280 | J11: =F11+I11 -> 9653.677 | K11: 9510 | L11: 894 | M11: 0.69 | N11: =J11/K11 -> 1.015108 | O11: =IFERROR(J11/L11,"n.m.") -> 10.798296 | P11: =IF(M11<0,"n.m.",D11/M11) -> 19.811594
B12: Puma SE | C12: PUM.DE | D12: 29.73 | E12: 147.2 | F12: =D12*E12 -> 4376.256 | G12: 3090 | H12: 432 | I12: =G12-H12 -> 2658 | J12: =F12+I12 -> 7034.256 | K12: 8320 | L12: 180 | M12: -4.88 | N12: =J12/K12 -> 0.84546346 | O12: =IFERROR(J12/L12,"n.m.") -> 39.0792 | P12: =IF(M12<0,"n.m.",D12/M12) -> n.m.
B13: Average | N13: =AVERAGE(N7:N12) -> 1.1804199 | O13: =AVERAGE(O7:O11) -> 10.505676 | P13: =AVERAGE(P7,P8,P10,P11) -> 15.481645
B14: Median | N14: =MEDIAN(N7:N12) -> 1.108412 | O14: =MEDIAN(O7:O11) -> 9.4051399 | P14: =MEDIAN(P7,P8,P10,P11) -> 16.129911
B16: Skechers (SKX) excluded -- taken private by 3G Capital, deal closed Sept-2025. Puma excluded from EV/EBITDA avg/median (transition-year margins). Under Armour and Puma excluded from P/E avg/median (loss-making, n.m.).
B18: NIKE IMPLIED VALUATION -- TRADING COMPS
B20: NIKE LTM Revenue | F20: =Model!F18 -> 46398
B21: NIKE LTM EBITDA | F21: =Model!F27-Model!F142 -> 4544
B22: NIKE LTM EPS (Diluted) | F22: =Model!F37 -> 2.098582
B23: Implied Enterprise Value -- EV/Revenue Method | F23: =F20*N13 -> 54769.122
B24: Implied Enterprise Value -- EV/EBITDA Method | F24: =F21*O13 -> 47737.793
B25: Less: Net Debt (FY26A) | F25: =Model!F64+Model!F65-Model!F44-Model!F45 -> -1085
B26: Implied Equity Value -- EV/Revenue Method | F26: =F23-F25 -> 55854.122
B27: Implied Equity Value -- EV/EBITDA Method | F27: =F24-F25 -> 48822.793
B28: Implied Equity Value -- P/E Method | F28: =F22*P13*F29 -> 48116.953
B29: Diluted Shares Outstanding (FY26A) | F29: =Model!F36 -> 1481
B30: Implied Share Price -- EV/Revenue Method | F30: =F26/F29 -> 37.71379
B31: Implied Share Price -- EV/EBITDA Method | F31: =F27/F29 -> 32.966099
B32: Implied Share Price -- P/E Method | F32: =F28/F29 -> 32.489502
B34: All figures in USD millions except per-share data. Market data as of late August 2026.
